[{"text":"وَالْعَصْرِ (1) إِنَّ الْإِنْسَانَ لَفِي خُسْرٍ (2) إِلَّا الَّذِينَ آمَنُوا","EndOfSurah":"0","aya":"1","SurahName":"العصر","page":"601"},{"text":"وَعَمِلُوا الصَّالِحَاتِ وَتَوَاصَوْا بِالْحَقِّ وَتَوَاصَوْا بِالصَّبْرِ (3)","EndOfSurah":"1","aya":"3","SurahName":"العصر","page":"601"},{"text":"وَيْلٌ لِكُلِّ هُمَزَةٍ لُمَزَةٍ (1) الَّذِي جَمَعَ مَالًا وَعَدَّدَهُ (2)","EndOfSurah":"0","aya":"1","SurahName":"الهمزة","page":"601"},{"text":"يَحْسَبُ أَنَّ مَالَهُ أَخْلَدَهُ (3) كَلَّا ۖ لَيُنْبَذَنَّ فِي الْحُطَمَةِ (4)","EndOfSurah":"0","aya":"3","SurahName":"الهمزة","page":"601"},{"text":"وَمَا أَدْرَاكَ مَا الْحُطَمَةُ (5) نَارُ اللَّهِ الْمُوقَدَةُ (6) الَّتِي تَطَّلِعُ","EndOfSurah":"1","aya":"5","SurahName":"الهمزة","page":"601"},{"text":"عَلَى الْأَفْئِدَةِ (7) إِنَّهَا عَلَيْهِمْ مُؤْصَدَةٌ (8) فِي عَمَدٍ مُمَدَّدَةٍ (9)","EndOfSurah":"0","aya":"7","SurahName":"الهمزة","page":"601"},{"text":"أَلَمْ تَرَ كَيْفَ فَعَلَ رَبُّكَ بِأَصْحَابِ الْفِيلِ (1) أَلَمْ يَجْعَلْ كَيْدَهُمْ","EndOfSurah":"0","aya":"1","SurahName":"القدر","page":"601"},{"text":"فِي تَضْلِيلٍ (2) وَأَرْسَلَ عَلَيْهِمْ طَيْرًا أَبَابِيلَ (3) تَرْمِيهِمْ","EndOfSurah":"0","aya":"2","SurahName":"القدر","page":"601"},{"text":"بِحِجَارَةٍ مِنْ سِجِّيلٍ (4) فَجَعَلَهُمْ كَعَصْفٍ مَأْكُولٍ (5)","EndOfSurah":"1","aya":"4","SurahName":"القدر","page":"601"}]