[
    {
        "text": "فَكَذَّبُوهُ فَإِنَّهُمْ لَمُحْضَرُونَ",
        "tafsir": "فكذبوه فيما جاءهم به من ضرورة عبادة الله وحده لا شريك له، وسيكونون يوم القيامة من المحضرين في العذاب في نار جهنم.\r\nلمحضرون- تحضرهم الزبانية في النار.",
        "sura": "37",
        "aya": "127",
        "page": "451"
    },
    {
        "text": "إِلَّا عِبَادَ ٱللَّهِ ٱلْمُخْلَصِينَ",
        "tafsir": "إلا الذين عبدوا الله من بينهم، وأخلصوا العبادة له، فهؤلاء لا يعذبهم الله في نار جهنم.",
        "sura": "37",
        "aya": "128",
        "page": "451"
    },
    {
        "text": "وَتَرَكْنَا عَلَيْهِ فِى ٱلْءَاخِرِينَ",
        "tafsir": "{ٱلآخِرِينَ} - وجعل الله ذكرا حسنا بين الناس تتناقله الأجيال، وجعله محببا إلى الناس جميعا.",
        "sura": "37",
        "aya": "129",
        "page": "451"
    },
    {
        "text": "سَلَٰمٌ عَلَىٰٓ إِلْ يَاسِينَ",
        "tafsir": "{إل ياسين} هو لغة في إياس، بزيادة الياء والنون؛ ونظيره سيناء وسينين. وقيل: هو جمع إلياس على التغليب بإطلاقه على قومه .",
        "sura": "37",
        "aya": "130",
        "page": "451"
    },
    {
        "text": "إِنَّا كَذَٰلِكَ نَجْزِى ٱلْمُحْسِنِينَ",
        "tafsir": "ومثل هذا الجزاء الحسن الذي جازى الله به نبيه إلياس، يجازي عباده المؤمنين السابقين المحسنين.",
        "sura": "37",
        "aya": "131",
        "page": "451"
    },
    {
        "text": "إِنَّهُۥ مِنْ عِبَادِنَا ٱلْمُؤْمِنِينَ",
        "tafsir": "وإن إلياس من عباد الله المؤمنين المخلصين.",
        "sura": "37",
        "aya": "132",
        "page": "451"
    },
    {
        "text": "وَإِنَّ لُوطًا لَّمِنَ ٱلْمُرْسَلِينَ",
        "tafsir": "وإن الله تعالى أرسل لوطا إلى أهل سدوم وكانوا قد أتوا من المنكرات ما لم يسبقهم إليه أحد من العالمين فنصحهم، وطالبهم بالكف عما هم عليه من الفساد، والكفر، والبغي، فلم ينتصحوا فأهلكهم الله جميعا.",
        "sura": "37",
        "aya": "133",
        "page": "451"
    },
    {
        "text": "إِذْ نَجَّيْنَٰهُ وَأَهْلَهُۥٓ أَجْمَعِينَ",
        "tafsir": "{نَجَّيْنَاهُ} - ونجى الله لوطا وأهله مما أنزله بقومه من العذاب والدمار.",
        "sura": "37",
        "aya": "134",
        "page": "451"
    },
    {
        "text": "إِلَّا عَجُوزًا فِى ٱلْغَٰبِرِينَ",
        "tafsir": "{إلا عجوزا في الغابرين} الباقين في العذاب .",
        "sura": "37",
        "aya": "135",
        "page": "451"
    },
    {
        "text": "ثُمَّ دَمَّرْنَا ٱلْءَاخَرِينَ",
        "tafsir": "{ٱلآخَرِينَ} - ثم أهلك الله القوم جميعا، فخسف بهم الأرض، وجعل عالي قريتهم سافلها، فلم ينج منهم أحد.",
        "sura": "37",
        "aya": "136",
        "page": "451"
    },
    {
        "text": "وَإِنَّكُمْ لَتَمُرُّونَ عَلَيْهِم مُّصْبِحِينَ",
        "tafsir": "وإنكم، يا معشر قريش، لتمرون بقرى قوم لوط مصبحين، وأنتم في طريقكم من مكة إلى الشام ذاهبين آيبين.\r\nمصبحين- داخلين في وقت الصباح.",
        "sura": "37",
        "aya": "137",
        "page": "451"
    },
    {
        "text": "وَبِٱلَّيْلِ أَفَلَا تَعْقِلُونَ",
        "tafsir": "{مصبحين وبالليل} أي في الصباح والمساء .",
        "sura": "37",
        "aya": "138",
        "page": "451"
    },
    {
        "text": "وَإِنَّ يُونُسَ لَمِنَ ٱلْمُرْسَلِينَ",
        "tafsir": "وإن يونس رسول من رسل الله تعالى، (وَقَدْ أَرْسَلَهُ اللهُ تَعَالَى إِلَى أَهْلِ نِينَوَى، وَكَانَتْ عَاصِمَةَ الآشُورِيِّينَ فِي وَقْتٍ مَا، وَهِيَ قُرْبَ المُوصِلِ) .",
        "sura": "37",
        "aya": "139",
        "page": "451"
    },
    {
        "text": "إِذْ أَبَقَ إِلَى ٱلْفُلْكِ ٱلْمَشْحُونِ",
        "tafsir": "{أبق} أي هرب من قومه بغير إذن ربه. يقال: أبق العبد– كضرب ومنع وسمع– هرب من سيده من غير خوف ولا كد عمل؛ فهو آبق. {المشحون} المملوء .",
        "sura": "37",
        "aya": "140",
        "page": "451"
    },
    {
        "text": "فَسَاهَمَ فَكَانَ مِنَ ٱلْمُدْحَضِينَ",
        "tafsir": "{فساهم} فقارع من في السفينة بالسهام. {فكان من المدحضين} أي المغلوبين بالقرعة. يقال: أدحض الله الحجة فدحضت؛ أي أبطلها فبطلت. والدحض في الأصل: الزلق في الماء والطين .",
        "sura": "37",
        "aya": "141",
        "page": "451"
    },
    {
        "text": "فَٱلْتَقَمَهُ ٱلْحُوتُ وَهُوَ مُلِيمٌ",
        "tafsir": "{فالتقمه الحوت} ابتلعه بسرعة؛ من لقم الشيء– كسمع- ،  ؟  والتقمه: أكله بسرعة. وتلقمه: ابتلعه في مهلة. وكان ذلك في نهر دجلة. {وهو مليم} أي مكتسب ما يلام عليه من مفارقة قومه بغير إذن ربه. يقال: ألام الرجل، إذا أتى ما يلام عليه من الأمر وإن لم يلم وأما الملوم: فهو الذي يلام، سواء أتى بما يستحق أن يلام عليه أم لا .",
        "sura": "37",
        "aya": "142",
        "page": "451"
    },
    {
        "text": "فَلَوْلَآ أَنَّهُۥ كَانَ مِنَ ٱلْمُسَبِّحِينَ",
        "tafsir": "ولو لم يكن من الذاكرين ربهم كثيرا، والمسبحين بحمده.",
        "sura": "37",
        "aya": "143",
        "page": "451"
    },
    {
        "text": "لَلَبِثَ فِى بَطْنِهِۦٓ إِلَىٰ يَوْمِ يُبْعَثُونَ",
        "tafsir": "للبث ميتا في بطن الحوت إلى يوم القيامة، يوم البعث والنشور، ولكان طعاما يتغذى به الحوت.",
        "sura": "37",
        "aya": "144",
        "page": "451"
    },
    {
        "text": "فَنَبَذْنَٰهُ بِٱلْعَرَآءِ وَهُوَ سَقِيمٌ",
        "tafsir": "{فنبذناه بالعراء} :  أمرنا الحوت بطرحه في الفضاء الواسع من الأرض، على شط النهر قرب نينوى من أرض\r\nالموصل، حيث لا يواريه شيء من شجر أو غيره؛ من النبذ وهو الطرح والإلقاء. والعراء: الأرض الواسعة لا نبات بها ولا معلم؛ مشتق من العرى وهو عدم السترة .",
        "sura": "37",
        "aya": "145",
        "page": "451"
    },
    {
        "text": "وَأَنۢبَتْنَا عَلَيْهِ شَجَرَةً مِّن يَقْطِينٍ",
        "tafsir": "{وأنبتنا عليه شجرة من يقطين} :  وللقرعة الرطبة: يقطينة .",
        "sura": "37",
        "aya": "146",
        "page": "451"
    },
    {
        "text": "وَأَرْسَلْنَٰهُ إِلَىٰ مِا۟ئَةِ أَلْفٍ أَوْ يَزِيدُونَ",
        "tafsir": "{أَرْسَلْنَاهُ} - ثم إنه بعد أن شفي، ورضي عليه ربه، بعثه الله تعالى رسولا إلى قومه مرة أخرى، وكان عددهم كثيرا قد يتجاوز مئة ألف، فاستقامت حالهم معه، لأنهم بعد خروجه عنهم، خافوا عذاب الله، وما أنذرهم به يونس، فخرجوا خارج البلد بأموالهم وأبنائهم ومواشيهم، وجأروا إلى الله بالدعاء، وأعلنوا التوبة لربهم، فأنجاهم ربهم من الهلاك، ولما عاد إليهم يونس التفوا حوله.",
        "sura": "37",
        "aya": "147",
        "page": "451"
    },
    {
        "text": "فَـَٔامَنُوا۟ فَمَتَّعْنَٰهُمْ إِلَىٰ حِينٍ",
        "tafsir": "{فَآمَنُواْ} {فَمَتَّعْنَاهُمْ} - فآمنوا بالله، وبما دعاهم إليه نبيهم يونس، فمتعهم الله في هذه الحياة الدنيا، حتى حانت آجالهم، فهلكوا فيمن هلك.",
        "sura": "37",
        "aya": "148",
        "page": "451"
    },
    {
        "text": "فَٱسْتَفْتِهِمْ أَلِرَبِّكَ ٱلْبَنَاتُ وَلَهُمُ ٱلْبَنُونَ",
        "tafsir": "{فاستفتهم} :  أي فاستفت كفار مكة، معطوف على قوله تعالى: {فاستفتهم أهم أشد خلقا} .",
        "sura": "37",
        "aya": "149",
        "page": "451"
    },
    {
        "text": "أَمْ خَلَقْنَا ٱلْمَلَٰٓئِكَةَ إِنَٰثًا وَهُمْ شَٰهِدُونَ",
        "tafsir": "{ٱلْمَلاَئِكَةَ} {إِنَاثاً} {شَاهِدُونَ} - وهل كانوا شهودا حين خلق الله الملائكة فرأوا أنه خلقهم إناثا؟ وبما أنهم لم يشهدوا خلق الله للملائكة، لذلك فإنهم يقولون ما لا يعرفون حقيقته، وليس لهم عليه دليل ولا حجة.",
        "sura": "37",
        "aya": "150",
        "page": "451"
    },
    {
        "text": "أَلَآ إِنَّهُم مِّنْ إِفْكِهِمْ لَيَقُولُونَ",
        "tafsir": "وما جرأهم على هذا القول الباطل إلا اعتقادهم كذبا وافتراء على الله:\r\nإفكهم- كذبهم على الله.",
        "sura": "37",
        "aya": "151",
        "page": "451"
    },
    {
        "text": "وَلَدَ ٱللَّهُ وَإِنَّهُمْ لَكَٰذِبُونَ",
        "tafsir": "{لَكَاذِبُونَ} - وقولهم إن لله ولدا. وهو افتراء قبيح، وإفك صريح لا مستند لهم فيه، ولا دليل لهم على صحته، وهم كاذبون فيما يقولون.",
        "sura": "37",
        "aya": "152",
        "page": "451"
    },
    {
        "text": "أَصْطَفَى ٱلْبَنَاتِ عَلَى ٱلْبَنِينَ",
        "tafsir": "وأي شيء يحمله على أن يختار لنفسه البنات ويترك لهم البنين؟ وكفار قريش يفضلون البنين على البنات ويختارون لأنفسهم البنين فيما لو كان لهم خيار.\r\nأصطفى- أختار- استفهام توبيخ.",
        "sura": "37",
        "aya": "153",
        "page": "451"
    }
]