[{"audio":"https:\/\/dl.salamquran.com\/ayat\/afasy-murattal-192\/042032.mp3"},{"audio":"https:\/\/dl.salamquran.com\/ayat\/afasy-murattal-192\/042033.mp3"},{"audio":"https:\/\/dl.salamquran.com\/ayat\/afasy-murattal-192\/042034.mp3"},{"audio":"https:\/\/dl.salamquran.com\/ayat\/afasy-murattal-192\/042035.mp3"},{"audio":"https:\/\/dl.salamquran.com\/ayat\/afasy-murattal-192\/042036.mp3"},{"audio":"https:\/\/dl.salamquran.com\/ayat\/afasy-murattal-192\/042037.mp3"},{"audio":"https:\/\/dl.salamquran.com\/ayat\/afasy-murattal-192\/042038.mp3"},{"audio":"https:\/\/dl.salamquran.com\/ayat\/afasy-murattal-192\/042039.mp3"},{"audio":"https:\/\/dl.salamquran.com\/ayat\/afasy-murattal-192\/042040.mp3"},{"audio":"https:\/\/dl.salamquran.com\/ayat\/afasy-murattal-192\/042041.mp3"},{"audio":"https:\/\/dl.salamquran.com\/ayat\/afasy-murattal-192\/042042.mp3"},{"audio":"https:\/\/dl.salamquran.com\/ayat\/afasy-murattal-192\/042043.mp3"},{"audio":"https:\/\/dl.salamquran.com\/ayat\/afasy-murattal-192\/042044.mp3"}]