[{"audio":"https:\/\/dl.salamquran.com\/ayat\/afasy-murattal-192\/015001.mp3","EndOfSurah":"0"},{"audio":"https:\/\/dl.salamquran.com\/ayat\/afasy-murattal-192\/015002.mp3","EndOfSurah":"0"},{"audio":"https:\/\/dl.salamquran.com\/ayat\/afasy-murattal-192\/015003.mp3","EndOfSurah":"0"},{"audio":"https:\/\/dl.salamquran.com\/ayat\/afasy-murattal-192\/015004.mp3","EndOfSurah":"0"},{"audio":"https:\/\/dl.salamquran.com\/ayat\/afasy-murattal-192\/015005.mp3","EndOfSurah":"0"},{"audio":"https:\/\/dl.salamquran.com\/ayat\/afasy-murattal-192\/015006.mp3","EndOfSurah":"0"},{"audio":"https:\/\/dl.salamquran.com\/ayat\/afasy-murattal-192\/015007.mp3","EndOfSurah":"0"},{"audio":"https:\/\/dl.salamquran.com\/ayat\/afasy-murattal-192\/015008.mp3","EndOfSurah":"0"},{"audio":"https:\/\/dl.salamquran.com\/ayat\/afasy-murattal-192\/015009.mp3","EndOfSurah":"0"},{"audio":"https:\/\/dl.salamquran.com\/ayat\/afasy-murattal-192\/015010.mp3","EndOfSurah":"0"},{"audio":"https:\/\/dl.salamquran.com\/ayat\/afasy-murattal-192\/015011.mp3","EndOfSurah":"0"},{"audio":"https:\/\/dl.salamquran.com\/ayat\/afasy-murattal-192\/015012.mp3","EndOfSurah":"0"},{"audio":"https:\/\/dl.salamquran.com\/ayat\/afasy-murattal-192\/015013.mp3","EndOfSurah":"0"},{"audio":"https:\/\/dl.salamquran.com\/ayat\/afasy-murattal-192\/015014.mp3","EndOfSurah":"0"},{"audio":"https:\/\/dl.salamquran.com\/ayat\/afasy-murattal-192\/015015.mp3","EndOfSurah":"0"}]