[{"audio":"https:\/\/dl.salamquran.com\/ayat\/afasy-murattal-192\/010079.mp3"},{"audio":"https:\/\/dl.salamquran.com\/ayat\/afasy-murattal-192\/010080.mp3"},{"audio":"https:\/\/dl.salamquran.com\/ayat\/afasy-murattal-192\/010081.mp3"},{"audio":"https:\/\/dl.salamquran.com\/ayat\/afasy-murattal-192\/010082.mp3"},{"audio":"https:\/\/dl.salamquran.com\/ayat\/afasy-murattal-192\/010083.mp3"},{"audio":"https:\/\/dl.salamquran.com\/ayat\/afasy-murattal-192\/010084.mp3"},{"audio":"https:\/\/dl.salamquran.com\/ayat\/afasy-murattal-192\/010085.mp3"},{"audio":"https:\/\/dl.salamquran.com\/ayat\/afasy-murattal-192\/010086.mp3"},{"audio":"https:\/\/dl.salamquran.com\/ayat\/afasy-murattal-192\/010087.mp3"},{"audio":"https:\/\/dl.salamquran.com\/ayat\/afasy-murattal-192\/010088.mp3"}]