[{"audio":"https:\/\/everyayah.com\/data\/Minshawy_Murattal_128kbps\/063005.mp3","EndOfSurah":"0"},{"audio":"https:\/\/everyayah.com\/data\/Minshawy_Murattal_128kbps\/063006.mp3","EndOfSurah":"0"},{"audio":"https:\/\/everyayah.com\/data\/Minshawy_Murattal_128kbps\/063007.mp3","EndOfSurah":"0"},{"audio":"https:\/\/everyayah.com\/data\/Minshawy_Murattal_128kbps\/063008.mp3","EndOfSurah":"0"},{"audio":"https:\/\/everyayah.com\/data\/Minshawy_Murattal_128kbps\/063009.mp3","EndOfSurah":"0"},{"audio":"https:\/\/everyayah.com\/data\/Minshawy_Murattal_128kbps\/063010.mp3","EndOfSurah":"0"},{"audio":"https:\/\/everyayah.com\/data\/Minshawy_Murattal_128kbps\/063011.mp3","EndOfSurah":"1"}]